blocky3D/__init__.py
blocky3D/engine.py
blocky3d-0.2.0.dist-info/METADATA
blocky3d-0.2.0.dist-info/WHEEL
blocky3d-0.2.0.dist-info/top_level.txt
blocky3d-0.2.0.dist-info/RECORD
