Metadata-Version: 2.4
Name: blocky3D
Version: 0.2.0
Summary: A fun and easy 3D block-building module for beginners!
Author: 히프마이
Author-email: youremail@example.com
Classifier: Programming Language :: Python :: 3
Classifier: Intended Audience :: Developers
Classifier: Topic :: Games/Entertainment
Classifier: License :: OSI Approved :: MIT License
Classifier: Operating System :: OS Independent
Requires-Python: >=3.6
Dynamic: author
Dynamic: author-email
Dynamic: classifier
Dynamic: description
Dynamic: description-content-type
Dynamic: requires-python
Dynamic: summary
